tf_tabular/__init__.py
tf_tabular/builder.py
tf_tabular/input_spec.py
tf_tabular/numeric_processor.py
tf_tabular/sequence_processor.py
tf_tabular/utils.py
tabular_tf-0.1.0.dist-info/LICENSE
tabular_tf-0.1.0.dist-info/WHEEL
tabular_tf-0.1.0.dist-info/METADATA
tabular_tf-0.1.0.dist-info/RECORD
