Metadata-Version: 2.1
Name: tabular-tf
Version: 0.1.0
Summary: TF Tabular simplifies the experimentation and preprocessing of tabular datsets for TensorFlow models.
Author-email: Mathias Claassen <mathias@xmartlabs.com>
Requires-Python: >=3.10
Classifier: Development Status :: 3 - Alpha
Classifier: Intended Audience :: Developers
Classifier: License :: OSI Approved :: MIT License
Classifier: Programming Language :: Python :: 3 :: Only
Classifier: Programming Language :: Python :: 3.10
Classifier: Programming Language :: Python :: 3.11
Requires-Dist: numpy >= 1.26
Requires-Dist: pandas >= 2.2.1
Requires-Dist: tensorflow <= 2.15.1
Requires-Dist: jupyter ; extra == "examples"
Requires-Dist: tensorflow_datasets >= 4.9.4 ; extra == "examples"
Requires-Dist: tensorflow-recommenders >= 0.7.3 ; extra == "examples"
Requires-Dist: matplotlib >= 3.8.4 ; extra == "examples"
Requires-Dist: ruff>=0.2.0 ; extra == "test"
Requires-Dist: mypy==1.10.0 ; extra == "test"
Requires-Dist: pre-commit==3.7.1 ; extra == "test"
Requires-Dist: pytest-cov==5.0.0 ; extra == "test"
Requires-Dist: pytest-mock<3.14.1 ; extra == "test"
Requires-Dist: pytest-runner ; extra == "test"
Requires-Dist: pytest==8.2.2 ; extra == "test"
Requires-Dist: pytest-github-actions-annotate-failures ; extra == "test"
Project-URL: Documentation, https://github.com/mats-claassen/tf-tabular/tree/main#readme
Project-URL: Source, https://github.com/mats-claassen/tf-tabular
Project-URL: Tracker, https://github.com/mats-claassen/tf-tabular/issues
Provides-Extra: examples
Provides-Extra: test
